qtreemesh/__init__.py
qtreemesh/_qtreemesh.py
qtreemesh-0.1.3.dist-info/LICENSE
qtreemesh-0.1.3.dist-info/METADATA
qtreemesh-0.1.3.dist-info/WHEEL
qtreemesh-0.1.3.dist-info/top_level.txt
qtreemesh-0.1.3.dist-info/RECORD
