Metadata-Version: 2.1
Name: qtreemesh
Version: 0.1.3
Summary: A package that creates quadtree mesh from an image
Home-page: https://github.com/Sad-Abd/qtreemesh
Author: Sad-Abd
Author-email: abedisadjad@gmail.com
Project-URL: Bug Tracker, https://github.com/Sad-Abd/qtreemesh/issues
Classifier: Programming Language :: Python :: 3
Classifier: License :: OSI Approved :: MIT License
Classifier: Operating System :: OS Independent
Requires-Python: >=3.7
License-File: LICENSE
